{
  "playlist": "MLG 4v4",
  "players": {
    "1136095104663306240": {
      "discord_name": "Hyrax",
      "xp": 1213,
      "rank": 13,
      "wins": 14,
      "losses": 8,
      "highest_rank": 13,
      "kills": 382,
      "deaths": 441,
      "assists": 258,
      "headshots": 261,
      "series_wins": 0,
      "series_losses": 0
    },
    "283293015135748097": {
      "discord_name": "Dirk",
      "xp": 0,
      "rank": 1,
      "wins": 0,
      "losses": 3,
      "highest_rank": 1,
      "kills": 45,
      "deaths": 66,
      "assists": 40,
      "headshots": 28,
      "series_wins": 0,
      "series_losses": 0
    },
    "269681242335739905": {
      "discord_name": "Keylord",
      "xp": 760,
      "rank": 8,
      "wins": 9,
      "losses": 22,
      "highest_rank": 6,
      "kills": 517,
      "deaths": 709,
      "assists": 435,
      "headshots": 340,
      "series_wins": 0,
      "series_losses": 0
    },
    "132652800378142720": {
      "discord_name": "Hammie",
      "xp": 765,
      "rank": 8,
      "wins": 8,
      "losses": 4,
      "highest_rank": 8,
      "kills": 302,
      "deaths": 298,
      "assists": 154,
      "headshots": 233,
      "series_wins": 0,
      "series_losses": 0
    },
    "136324687926919168": {
      "discord_name": "roasted",
      "xp": 181,
      "rank": 2,
      "wins": 2,
      "losses": 6,
      "highest_rank": 3,
      "kills": 98,
      "deaths": 195,
      "assists": 87,
      "headshots": 54,
      "series_wins": 0,
      "series_losses": 0
    },
    "426757496557010948": {
      "discord_name": "Rocky",
      "xp": 490,
      "rank": 6,
      "wins": 5,
      "losses": 3,
      "highest_rank": 6,
      "kills": 185,
      "deaths": 151,
      "assists": 79,
      "headshots": 118,
      "series_wins": 0,
      "series_losses": 0
    },
    "293507586131492864": {
      "discord_name": "Prince KidMode",
      "xp": 1042,
      "rank": 11,
      "wins": 11,
      "losses": 5,
      "highest_rank": 11,
      "kills": 310,
      "deaths": 325,
      "assists": 201,
      "headshots": 214,
      "series_wins": 0,
      "series_losses": 0
    },
    "284010072504270849": {
      "discord_name": "DU7S",
      "xp": 98,
      "rank": 2,
      "wins": 1,
      "losses": 3,
      "highest_rank": 2,
      "kills": 41,
      "deaths": 70,
      "assists": 40,
      "headshots": 22,
      "series_wins": 0,
      "series_losses": 0
    },
    "210187331066396672": {
      "discord_name": "Rinser",
      "xp": 700,
      "rank": 8,
      "wins": 7,
      "losses": 1,
      "highest_rank": 5,
      "kills": 158,
      "deaths": 134,
      "assists": 79,
      "headshots": 113,
      "series_wins": 0,
      "series_losses": 0
    },
    "334212655613214721": {
      "discord_name": "fluhd",
      "xp": 1418,
      "rank": 14,
      "wins": 17,
      "losses": 11,
      "highest_rank": 14,
      "kills": 670,
      "deaths": 537,
      "assists": 323,
      "headshots": 440,
      "series_wins": 0,
      "series_losses": 0
    },
    "859153194839965718": {
      "discord_name": "Curts GLORY",
      "xp": 98,
      "rank": 2,
      "wins": 1,
      "losses": 3,
      "highest_rank": 2,
      "kills": 71,
      "deaths": 62,
      "assists": 45,
      "headshots": 49,
      "series_wins": 0,
      "series_losses": 0
    },
    "652998057087991838": {
      "discord_name": "TwoDashAngo",
      "xp": 296,
      "rank": 4,
      "wins": 3,
      "losses": 2,
      "highest_rank": 4,
      "kills": 74,
      "deaths": 102,
      "assists": 57,
      "headshots": 50,
      "series_wins": 0,
      "series_losses": 0
    },
    "314217230390919174": {
      "discord_name": "popq2",
      "xp": 660,
      "rank": 7,
      "wins": 7,
      "losses": 10,
      "highest_rank": 6,
      "kills": 261,
      "deaths": 255,
      "assists": 197,
      "headshots": 149,
      "series_wins": 0,
      "series_losses": 0
    },
    "797210177786347530": {
      "discord_name": "future trunks",
      "xp": 98,
      "rank": 2,
      "wins": 1,
      "losses": 4,
      "highest_rank": 2,
      "kills": 112,
      "deaths": 105,
      "assists": 76,
      "headshots": 70,
      "series_wins": 0,
      "series_losses": 0
    },
    "161726300304834560": {
      "discord_name": "Jay2",
      "xp": 371,
      "rank": 4,
      "wins": 4,
      "losses": 5,
      "highest_rank": 4,
      "kills": 154,
      "deaths": 224,
      "assists": 122,
      "headshots": 115,
      "series_wins": 0,
      "series_losses": 0
    },
    "164725201907613696": {
      "discord_name": "James | The Frenetic",
      "xp": 270,
      "rank": 3,
      "wins": 3,
      "losses": 8,
      "highest_rank": 4,
      "kills": 321,
      "deaths": 309,
      "assists": 170,
      "headshots": 235,
      "series_wins": 0,
      "series_losses": 0
    },
    "1040724126836457624": {
      "discord_name": "M15F1T",
      "xp": 693,
      "rank": 8,
      "wins": 7,
      "losses": 1,
      "highest_rank": 5,
      "kills": 182,
      "deaths": 211,
      "assists": 112,
      "headshots": 139,
      "series_wins": 0,
      "series_losses": 0
    },
    "274372368686776321": {
      "discord_name": "sneakybeav3r",
      "xp": 673,
      "rank": 7,
      "wins": 8,
      "losses": 8,
      "highest_rank": 8,
      "kills": 407,
      "deaths": 318,
      "assists": 188,
      "headshots": 269,
      "series_wins": 0,
      "series_losses": 0
    },
    "390747330631958528": {
      "discord_name": "cOn",
      "xp": 861,
      "rank": 9,
      "wins": 10,
      "losses": 8,
      "highest_rank": 9,
      "kills": 413,
      "deaths": 372,
      "assists": 288,
      "headshots": 271,
      "series_wins": 0,
      "series_losses": 0
    },
    "111190770756657152": {
      "discord_name": "EpiiiC",
      "xp": 912,
      "rank": 10,
      "wins": 11,
      "losses": 12,
      "highest_rank": 11,
      "kills": 555,
      "deaths": 501,
      "assists": 343,
      "headshots": 394,
      "series_wins": 0,
      "series_losses": 0
    },
    "168151188741685248": {
      "discord_name": "AfroMaN",
      "xp": 750,
      "rank": 8,
      "wins": 8,
      "losses": 10,
      "highest_rank": 8,
      "kills": 466,
      "deaths": 368,
      "assists": 261,
      "headshots": 311,
      "series_wins": 0,
      "series_losses": 0
    },
    "175060415833833472": {
      "discord_name": "Tetracide",
      "xp": 296,
      "rank": 4,
      "wins": 3,
      "losses": 2,
      "highest_rank": 4,
      "kills": 97,
      "deaths": 79,
      "assists": 48,
      "headshots": 69,
      "series_wins": 0,
      "series_losses": 0
    }
  }
}