{
  "1136095104663306240": {
    "discord_name": "Hyrax",
    "alias": "",
    "twitch_name": "hyrax__",
    "twitch_url": "https://twitch.tv/hyrax__",
    "rank": 13,
    "highest_rank": 13,
    "xp": 1213,
    "mmr": 950,
    "wins": 14,
    "losses": 8,
    "total_games": 27,
    "kills": 382,
    "deaths": 441,
    "assists": 258,
    "headshots": 261,
    "series_wins": 3,
    "series_losses": 1,
    "playlists": {
      "MLG 4v4": {
        "rank": 13,
        "highest_rank": 13,
        "xp": 1213,
        "wins": 14,
        "losses": 8,
        "games": 24
      }
    }
  },
  "283293015135748097": {
    "discord_name": "Dirk",
    "alias": "Dirk",
    "twitch_name": "ogdirk",
    "twitch_url": "https://twitch.tv/ogdirk",
    "rank": 1,
    "highest_rank": 1,
    "xp": 0,
    "mmr": 900,
    "wins": 0,
    "losses": 3,
    "total_games": 3,
    "kills": 45,
    "deaths": 66,
    "assists": 40,
    "headshots": 28,
    "series_wins": 0,
    "series_losses": 1,
    "playlists": {
      "MLG 4v4": {
        "rank": 1,
        "highest_rank": 1,
        "xp": 0,
        "wins": 0,
        "losses": 3,
        "games": 3
      }
    }
  },
  "132652800378142720": {
    "discord_name": "Hammie",
    "alias": "Hammie",
    "twitch_name": "ai2ejay",
    "twitch_url": "https://twitch.tv/ai2ejay",
    "rank": 8,
    "highest_rank": 8,
    "xp": 765,
    "mmr": 1100,
    "wins": 8,
    "losses": 4,
    "total_games": 15,
    "kills": 302,
    "deaths": 298,
    "assists": 154,
    "headshots": 233,
    "series_wins": 2,
    "series_losses": 0,
    "playlists": {
      "MLG 4v4": {
        "rank": 8,
        "highest_rank": 8,
        "xp": 765,
        "wins": 8,
        "losses": 4,
        "games": 13
      }
    }
  },
  "136324687926919168": {
    "discord_name": "roasted",
    "alias": "roasted",
    "twitch_name": "h2roasted",
    "twitch_url": "https://twitch.tv/h2roasted",
    "rank": 2,
    "highest_rank": 3,
    "xp": 181,
    "mmr": 750,
    "wins": 2,
    "losses": 6,
    "total_games": 8,
    "kills": 98,
    "deaths": 195,
    "assists": 87,
    "headshots": 54,
    "series_wins": 0,
    "series_losses": 2,
    "playlists": {
      "MLG 4v4": {
        "rank": 2,
        "highest_rank": 3,
        "xp": 181,
        "wins": 2,
        "losses": 6,
        "games": 8
      }
    }
  },
  "426757496557010948": {
    "discord_name": "Rocky",
    "alias": "Rocky",
    "twitch_name": "c6rocky",
    "twitch_url": "https://twitch.tv/c6rocky",
    "rank": 6,
    "highest_rank": 6,
    "xp": 490,
    "mmr": 1075,
    "wins": 5,
    "losses": 3,
    "total_games": 8,
    "kills": 185,
    "deaths": 151,
    "assists": 79,
    "headshots": 118,
    "series_wins": 1,
    "series_losses": 1,
    "playlists": {
      "MLG 4v4": {
        "rank": 6,
        "highest_rank": 6,
        "xp": 490,
        "wins": 5,
        "losses": 3,
        "games": 8
      }
    }
  },
  "412829053603807232": {
    "discord_name": "Lefty",
    "alias": "",
    "twitch_name": "",
    "twitch_url": "",
    "rank": 1,
    "highest_rank": 1,
    "xp": 0,
    "mmr": 700,
    "wins": 0,
    "losses": 0,
    "total_games": 0,
    "kills": 0,
    "deaths": 0,
    "assists": 0,
    "headshots": 0,
    "series_wins": 0,
    "series_losses": 0,
    "playlists": {}
  },
  "232556390839746560": {
    "discord_name": "DSJ",
    "alias": "",
    "twitch_name": "",
    "twitch_url": "",
    "rank": 1,
    "highest_rank": 1,
    "xp": 0,
    "mmr": 925,
    "wins": 0,
    "losses": 0,
    "total_games": 0,
    "kills": 0,
    "deaths": 0,
    "assists": 0,
    "headshots": 0,
    "series_wins": 0,
    "series_losses": 0,
    "playlists": {}
  },
  "293794892893782017": {
    "discord_name": "FrEnZy",
    "alias": "",
    "twitch_name": "trailerparkrich",
    "twitch_url": "https://twitch.tv/trailerparkrich",
    "rank": 1,
    "highest_rank": 1,
    "xp": 0,
    "mmr": 900,
    "wins": 0,
    "losses": 0,
    "total_games": 0,
    "kills": 0,
    "deaths": 0,
    "assists": 0,
    "headshots": 0,
    "series_wins": 0,
    "series_losses": 0,
    "playlists": {}
  },
  "293507586131492864": {
    "discord_name": "Prince KidMode",
    "alias": "KidMode",
    "twitch_name": "kidm0de",
    "twitch_url": "https://twitch.tv/kidm0de",
    "rank": 11,
    "highest_rank": 11,
    "xp": 1049,
    "mmr": 1100,
    "wins": 11,
    "losses": 4,
    "total_games": 17,
    "kills": 310,
    "deaths": 325,
    "assists": 201,
    "headshots": 214,
    "series_wins": 3,
    "series_losses": 0,
    "playlists": {
      "MLG 4v4": {
        "rank": 11,
        "highest_rank": 11,
        "xp": 1049,
        "wins": 11,
        "losses": 4,
        "games": 15
      }
    }
  },
  "284010072504270849": {
    "discord_name": "DU7S",
    "alias": "",
    "twitch_name": "du7s",
    "twitch_url": "https://twitch.tv/du7s",
    "rank": 2,
    "highest_rank": 2,
    "xp": 98,
    "mmr": 750,
    "wins": 1,
    "losses": 3,
    "total_games": 5,
    "kills": 41,
    "deaths": 70,
    "assists": 40,
    "headshots": 22,
    "series_wins": 0,
    "series_losses": 1,
    "playlists": {
      "MLG 4v4": {
        "rank": 2,
        "highest_rank": 2,
        "xp": 98,
        "wins": 1,
        "losses": 3,
        "games": 5
      }
    }
  },
  "299780772456431627": {
    "discord_name": "Gava",
    "alias": "",
    "twitch_name": "",
    "twitch_url": "",
    "rank": 1,
    "highest_rank": 1,
    "xp": 0,
    "mmr": 800,
    "wins": 0,
    "losses": 0,
    "total_games": 0,
    "kills": 0,
    "deaths": 0,
    "assists": 0,
    "headshots": 0,
    "series_wins": 0,
    "series_losses": 0,
    "playlists": {}
  },
  "210187331066396672": {
    "discord_name": "Rinser",
    "alias": "Rinser",
    "twitch_name": "mrwelfares",
    "twitch_url": "https://twitch.tv/mrwelfares",
    "rank": 8,
    "highest_rank": 5,
    "xp": 700,
    "mmr": 800,
    "wins": 7,
    "losses": 0,
    "total_games": 9,
    "kills": 158,
    "deaths": 134,
    "assists": 79,
    "headshots": 113,
    "series_wins": 2,
    "series_losses": 0,
    "playlists": {
      "MLG 4v4": {
        "rank": 8,
        "highest_rank": 5,
        "xp": 700,
        "wins": 7,
        "losses": 0,
        "games": 7
      }
    }
  },
  "334212655613214721": {
    "discord_name": "fluhd",
    "alias": "getitoutdaFLUD",
    "twitch_name": "floodandshiro",
    "twitch_url": "https://twitch.tv/floodandshiro",
    "rank": 14,
    "highest_rank": 14,
    "xp": 1418,
    "mmr": 1400,
    "wins": 17,
    "losses": 11,
    "total_games": 32,
    "kills": 670,
    "deaths": 537,
    "assists": 323,
    "headshots": 440,
    "series_wins": 3,
    "series_losses": 3,
    "playlists": {
      "MLG 4v4": {
        "rank": 14,
        "highest_rank": 14,
        "xp": 1418,
        "wins": 17,
        "losses": 11,
        "games": 30
      }
    }
  },
  "212720585279537153": {
    "discord_name": "Punny88",
    "alias": "",
    "twitch_name": "",
    "twitch_url": "",
    "rank": 1,
    "highest_rank": 1,
    "xp": 0,
    "mmr": 711,
    "wins": 0,
    "losses": 0,
    "total_games": 0,
    "kills": 0,
    "deaths": 0,
    "assists": 0,
    "headshots": 0,
    "series_wins": 0,
    "series_losses": 0,
    "playlists": {}
  },
  "385632391089356810": {
    "discord_name": "KraN",
    "alias": "",
    "twitch_name": "kranlive",
    "twitch_url": "https://twitch.tv/kranlive",
    "rank": 1,
    "highest_rank": 1,
    "xp": 0,
    "mmr": 950,
    "wins": 0,
    "losses": 0,
    "total_games": 0,
    "kills": 0,
    "deaths": 0,
    "assists": 0,
    "headshots": 0,
    "series_wins": 0,
    "series_losses": 0,
    "playlists": {}
  },
  "1222926448084520970": {
    "discord_name": "Old Man",
    "alias": "",
    "twitch_name": "old_man_halo",
    "twitch_url": "https://twitch.tv/old_man_halo",
    "rank": 1,
    "highest_rank": 1,
    "xp": 0,
    "mmr": 250,
    "wins": 0,
    "losses": 0,
    "total_games": 0,
    "kills": 0,
    "deaths": 0,
    "assists": 0,
    "headshots": 0,
    "series_wins": 0,
    "series_losses": 0,
    "playlists": {}
  },
  "165626999891689474": {
    "discord_name": "SHOW5TOPPER",
    "alias": "",
    "twitch_name": "",
    "twitch_url": "",
    "rank": 1,
    "highest_rank": 1,
    "xp": 0,
    "mmr": 950,
    "wins": 0,
    "losses": 0,
    "total_games": 0,
    "kills": 0,
    "deaths": 0,
    "assists": 0,
    "headshots": 0,
    "series_wins": 0,
    "series_losses": 0,
    "playlists": {}
  },
  "486628967760003085": {
    "discord_name": "NaDeShY",
    "alias": "",
    "twitch_name": "nadeshy",
    "twitch_url": "https://twitch.tv/nadeshy",
    "rank": 1,
    "highest_rank": 1,
    "xp": 0,
    "mmr": 950,
    "wins": 0,
    "losses": 0,
    "total_games": 0,
    "kills": 0,
    "deaths": 0,
    "assists": 0,
    "headshots": 0,
    "series_wins": 0,
    "series_losses": 0,
    "playlists": {}
  },
  "558138736966238219": {
    "discord_name": "waRRior Fresh",
    "alias": "",
    "twitch_name": "",
    "twitch_url": "",
    "rank": 1,
    "highest_rank": 1,
    "xp": 0,
    "mmr": 1200,
    "wins": 0,
    "losses": 0,
    "total_games": 0,
    "kills": 0,
    "deaths": 0,
    "assists": 0,
    "headshots": 0,
    "series_wins": 0,
    "series_losses": 0,
    "playlists": {}
  },
  "294558721474953219": {
    "discord_name": "bignami",
    "alias": "",
    "twitch_name": "",
    "twitch_url": "",
    "rank": 1,
    "highest_rank": 1,
    "xp": 0,
    "mmr": 750,
    "wins": 0,
    "losses": 0,
    "total_games": 0,
    "kills": 0,
    "deaths": 0,
    "assists": 0,
    "headshots": 0,
    "series_wins": 0,
    "series_losses": 0,
    "playlists": {}
  },
  "395302282914168852": {
    "discord_name": "TimRager",
    "alias": "",
    "twitch_name": "",
    "twitch_url": "",
    "rank": 1,
    "highest_rank": 1,
    "xp": 0,
    "mmr": 1550,
    "wins": 0,
    "losses": 0,
    "total_games": 0,
    "kills": 0,
    "deaths": 0,
    "assists": 0,
    "headshots": 0,
    "series_wins": 0,
    "series_losses": 0,
    "playlists": {}
  },
  "859153194839965718": {
    "discord_name": "Curts GLORY",
    "alias": "",
    "twitch_name": "Curtsglory",
    "twitch_url": "https://twitch.tv/Curtsglory",
    "rank": 2,
    "highest_rank": 2,
    "xp": 98,
    "mmr": 1150,
    "wins": 1,
    "losses": 3,
    "total_games": 5,
    "kills": 71,
    "deaths": 62,
    "assists": 45,
    "headshots": 49,
    "series_wins": 0,
    "series_losses": 1,
    "playlists": {
      "MLG 4v4": {
        "rank": 2,
        "highest_rank": 2,
        "xp": 98,
        "wins": 1,
        "losses": 3,
        "games": 5
      }
    }
  },
  "943239550782803988": {
    "discord_name": "xX daVe Xx",
    "alias": "",
    "twitch_name": "",
    "twitch_url": "",
    "rank": 1,
    "highest_rank": 1,
    "xp": 0,
    "mmr": 600,
    "wins": 0,
    "losses": 0,
    "total_games": 0,
    "kills": 0,
    "deaths": 0,
    "assists": 0,
    "headshots": 0,
    "series_wins": 0,
    "series_losses": 0,
    "playlists": {}
  },
  "771859735938072596": {
    "discord_name": "JUiCE",
    "alias": "",
    "twitch_name": "",
    "twitch_url": "",
    "rank": 1,
    "highest_rank": 1,
    "xp": 0,
    "mmr": 700,
    "wins": 0,
    "losses": 0,
    "total_games": 0,
    "kills": 0,
    "deaths": 0,
    "assists": 0,
    "headshots": 0,
    "series_wins": 0,
    "series_losses": 0,
    "playlists": {}
  },
  "554332927614517269": {
    "discord_name": "TGS NaTuRaL",
    "alias": "",
    "twitch_name": "",
    "twitch_url": "",
    "rank": 1,
    "highest_rank": 1,
    "xp": 0,
    "mmr": 900,
    "wins": 0,
    "losses": 0,
    "total_games": 0,
    "kills": 0,
    "deaths": 0,
    "assists": 0,
    "headshots": 0,
    "series_wins": 0,
    "series_losses": 0,
    "playlists": {}
  },
  "658102055696859156": {
    "discord_name": "-NeiLuZ-",
    "alias": "",
    "twitch_name": "",
    "twitch_url": "",
    "rank": 1,
    "highest_rank": 1,
    "xp": 0,
    "mmr": 500,
    "wins": 0,
    "losses": 0,
    "total_games": 0,
    "kills": 0,
    "deaths": 0,
    "assists": 0,
    "headshots": 0,
    "series_wins": 0,
    "series_losses": 0,
    "playlists": {}
  },
  "384701805944111128": {
    "discord_name": "Overseasons",
    "alias": "",
    "twitch_name": "",
    "twitch_url": "",
    "rank": 1,
    "highest_rank": 1,
    "xp": 0,
    "mmr": 750,
    "wins": 0,
    "losses": 0,
    "total_games": 0,
    "kills": 0,
    "deaths": 0,
    "assists": 0,
    "headshots": 0,
    "series_wins": 0,
    "series_losses": 0,
    "playlists": {}
  },
  "141912473744703489": {
    "discord_name": "LiaM",
    "alias": "",
    "twitch_name": "",
    "twitch_url": "",
    "rank": 1,
    "highest_rank": 1,
    "xp": 0,
    "mmr": 600,
    "wins": 0,
    "losses": 0,
    "total_games": 0,
    "kills": 0,
    "deaths": 0,
    "assists": 0,
    "headshots": 0,
    "series_wins": 0,
    "series_losses": 0,
    "playlists": {}
  },
  "556272092408971294": {
    "discord_name": "Dro",
    "alias": "",
    "twitch_name": "",
    "twitch_url": "",
    "rank": 1,
    "highest_rank": 1,
    "xp": 0,
    "mmr": 1300,
    "wins": 0,
    "losses": 0,
    "total_games": 0,
    "kills": 0,
    "deaths": 0,
    "assists": 0,
    "headshots": 0,
    "series_wins": 0,
    "series_losses": 0,
    "playlists": {}
  },
  "156907171433414656": {
    "discord_name": "Lethal_HT",
    "alias": "lethal_ht",
    "twitch_name": "lethal_ht",
    "twitch_url": "https://twitch.tv/lethal_ht",
    "rank": 1,
    "highest_rank": 1,
    "xp": 0,
    "mmr": 1050,
    "wins": 0,
    "losses": 0,
    "total_games": 0,
    "kills": 0,
    "deaths": 0,
    "assists": 0,
    "headshots": 0,
    "series_wins": 0,
    "series_losses": 0,
    "playlists": {}
  },
  "900612436686680095": {
    "discord_name": "T.Robs",
    "alias": "",
    "twitch_name": "",
    "twitch_url": "",
    "rank": 1,
    "highest_rank": 1,
    "xp": 0,
    "mmr": 300,
    "wins": 0,
    "losses": 0,
    "total_games": 0,
    "kills": 0,
    "deaths": 0,
    "assists": 0,
    "headshots": 0,
    "series_wins": 0,
    "series_losses": 0,
    "playlists": {}
  },
  "652998057087991838": {
    "discord_name": "TwoDashAngo",
    "alias": "2D",
    "twitch_name": "",
    "twitch_url": "",
    "rank": 4,
    "highest_rank": 4,
    "xp": 296,
    "mmr": 900,
    "wins": 3,
    "losses": 2,
    "total_games": 5,
    "kills": 74,
    "deaths": 102,
    "assists": 57,
    "headshots": 50,
    "series_wins": 1,
    "series_losses": 0,
    "playlists": {
      "MLG 4v4": {
        "rank": 4,
        "highest_rank": 4,
        "xp": 296,
        "wins": 3,
        "losses": 2,
        "games": 5
      }
    }
  },
  "1380083223937290272": {
    "discord_name": "Mr i Hockey",
    "alias": "",
    "twitch_name": "",
    "twitch_url": "",
    "rank": 1,
    "highest_rank": 1,
    "xp": 0,
    "mmr": 950,
    "wins": 0,
    "losses": 0,
    "total_games": 0,
    "kills": 0,
    "deaths": 0,
    "assists": 0,
    "headshots": 0,
    "series_wins": 0,
    "series_losses": 0,
    "playlists": {}
  },
  "314217230390919174": {
    "discord_name": "popq22",
    "alias": "popq22",
    "twitch_name": "",
    "twitch_url": "",
    "rank": 7,
    "highest_rank": 6,
    "xp": 660,
    "mmr": 850,
    "wins": 7,
    "losses": 10,
    "total_games": 19,
    "kills": 261,
    "deaths": 255,
    "assists": 197,
    "headshots": 149,
    "series_wins": 1,
    "series_losses": 2,
    "playlists": {
      "MLG 4v4": {
        "rank": 7,
        "highest_rank": 6,
        "xp": 660,
        "wins": 7,
        "losses": 10,
        "games": 18
      }
    }
  },
  "1179648030375424032": {
    "discord_name": "Ben",
    "alias": "",
    "twitch_name": "",
    "twitch_url": "",
    "rank": 1,
    "highest_rank": 1,
    "xp": 0,
    "mmr": 1200,
    "wins": 0,
    "losses": 0,
    "total_games": 0,
    "kills": 0,
    "deaths": 0,
    "assists": 0,
    "headshots": 0,
    "series_wins": 0,
    "series_losses": 0,
    "playlists": {}
  },
  "1324420042494050338": {
    "discord_name": "DrugAbuse goose \ud83c\uddfa\ud83c\uddf8",
    "alias": "",
    "twitch_name": "",
    "twitch_url": "",
    "rank": 1,
    "highest_rank": 1,
    "xp": 0,
    "mmr": 800,
    "wins": 0,
    "losses": 0,
    "total_games": 0,
    "kills": 0,
    "deaths": 0,
    "assists": 0,
    "headshots": 0,
    "series_wins": 0,
    "series_losses": 0,
    "playlists": {}
  },
  "359216128959971329": {
    "discord_name": "Hypnox",
    "alias": "Hypnosis",
    "twitch_name": "hyp_nox",
    "twitch_url": "https://twitch.tv/hyp_nox",
    "rank": 1,
    "highest_rank": 1,
    "xp": 0,
    "mmr": 1650,
    "wins": 0,
    "losses": 0,
    "total_games": 0,
    "kills": 0,
    "deaths": 0,
    "assists": 0,
    "headshots": 0,
    "series_wins": 0,
    "series_losses": 0,
    "playlists": {}
  },
  "276552139084398592": {
    "discord_name": "WoGG",
    "alias": "",
    "twitch_name": "",
    "twitch_url": "",
    "rank": 1,
    "highest_rank": 1,
    "xp": 0,
    "mmr": 1325,
    "wins": 0,
    "losses": 0,
    "total_games": 0,
    "kills": 0,
    "deaths": 0,
    "assists": 0,
    "headshots": 0,
    "series_wins": 0,
    "series_losses": 0,
    "playlists": {}
  },
  "639932733392683048": {
    "discord_name": "fricken (retired)",
    "alias": "",
    "twitch_name": "",
    "twitch_url": "",
    "rank": 1,
    "highest_rank": 1,
    "xp": 0,
    "mmr": 1300,
    "wins": 0,
    "losses": 0,
    "total_games": 0,
    "kills": 0,
    "deaths": 0,
    "assists": 0,
    "headshots": 0,
    "series_wins": 0,
    "series_losses": 0,
    "playlists": {}
  },
  "980246369161855017": {
    "discord_name": "Byceps",
    "alias": "",
    "twitch_name": "",
    "twitch_url": "",
    "rank": 1,
    "highest_rank": 1,
    "xp": 0,
    "mmr": 500,
    "wins": 0,
    "losses": 0,
    "total_games": 0,
    "kills": 0,
    "deaths": 0,
    "assists": 0,
    "headshots": 0,
    "series_wins": 0,
    "series_losses": 0,
    "playlists": {}
  },
  "884896715432411178": {
    "discord_name": "I2aMpAnT",
    "alias": "",
    "twitch_name": "i2ampant_Gaming",
    "twitch_url": "https://twitch.tv/i2ampant_Gaming",
    "rank": 1,
    "highest_rank": 1,
    "xp": 0,
    "mmr": 850,
    "wins": 0,
    "losses": 0,
    "total_games": 1,
    "kills": 0,
    "deaths": 1,
    "assists": 0,
    "headshots": 0,
    "series_wins": 0,
    "series_losses": 0,
    "playlists": {}
  },
  "601594438233620521": {
    "discord_name": "MadMikeWillEatU",
    "alias": "",
    "twitch_name": "",
    "twitch_url": "",
    "rank": 1,
    "highest_rank": 1,
    "xp": 0,
    "mmr": 1000,
    "wins": 0,
    "losses": 0,
    "total_games": 0,
    "kills": 0,
    "deaths": 0,
    "assists": 0,
    "headshots": 0,
    "series_wins": 0,
    "series_losses": 0,
    "playlists": {}
  },
  "173926727117045760": {
    "discord_name": "Gor3",
    "alias": "",
    "twitch_name": "",
    "twitch_url": "",
    "rank": 1,
    "highest_rank": 1,
    "xp": 0,
    "mmr": 1650,
    "wins": 0,
    "losses": 0,
    "total_games": 0,
    "kills": 0,
    "deaths": 0,
    "assists": 0,
    "headshots": 0,
    "series_wins": 0,
    "series_losses": 0,
    "playlists": {}
  },
  "907034559248482314": {
    "discord_name": "MohnJorrow",
    "alias": "",
    "twitch_name": "",
    "twitch_url": "",
    "rank": 1,
    "highest_rank": 1,
    "xp": 0,
    "mmr": 200,
    "wins": 0,
    "losses": 0,
    "total_games": 0,
    "kills": 0,
    "deaths": 0,
    "assists": 0,
    "headshots": 0,
    "series_wins": 0,
    "series_losses": 0,
    "playlists": {}
  },
  "951202518396977203": {
    "discord_name": "Wrecktangle\u2019s Mic",
    "alias": "",
    "twitch_name": "",
    "twitch_url": "",
    "rank": 1,
    "highest_rank": 1,
    "xp": 0,
    "mmr": 362,
    "wins": 0,
    "losses": 0,
    "total_games": 0,
    "kills": 0,
    "deaths": 0,
    "assists": 0,
    "headshots": 0,
    "series_wins": 0,
    "series_losses": 0,
    "playlists": {}
  },
  "797210177786347530": {
    "discord_name": "future trunks",
    "alias": "future trunks",
    "twitch_name": "",
    "twitch_url": "",
    "rank": 2,
    "highest_rank": 2,
    "xp": 98,
    "mmr": 1200,
    "wins": 1,
    "losses": 4,
    "total_games": 7,
    "kills": 112,
    "deaths": 105,
    "assists": 76,
    "headshots": 70,
    "series_wins": 0,
    "series_losses": 1,
    "playlists": {
      "MLG 4v4": {
        "rank": 2,
        "highest_rank": 2,
        "xp": 98,
        "wins": 1,
        "losses": 4,
        "games": 6
      }
    }
  },
  "213096674023833610": {
    "discord_name": "Faulty",
    "alias": "",
    "twitch_name": "texjas",
    "twitch_url": "https://twitch.tv/texjas",
    "rank": 1,
    "highest_rank": 1,
    "xp": 0,
    "mmr": 800,
    "wins": 0,
    "losses": 0,
    "total_games": 0,
    "kills": 0,
    "deaths": 0,
    "assists": 0,
    "headshots": 0,
    "series_wins": 0,
    "series_losses": 0,
    "playlists": {}
  },
  "176191518837702666": {
    "discord_name": "J2",
    "alias": "",
    "twitch_name": "",
    "twitch_url": "",
    "rank": 1,
    "highest_rank": 1,
    "xp": 0,
    "mmr": 900,
    "wins": 0,
    "losses": 0,
    "total_games": 0,
    "kills": 0,
    "deaths": 0,
    "assists": 0,
    "headshots": 0,
    "series_wins": 0,
    "series_losses": 0,
    "playlists": {}
  },
  "225563156397686786": {
    "discord_name": "Sup",
    "alias": "",
    "twitch_name": "",
    "twitch_url": "",
    "rank": 1,
    "highest_rank": 1,
    "xp": 0,
    "mmr": 900,
    "wins": 0,
    "losses": 0,
    "total_games": 0,
    "kills": 0,
    "deaths": 0,
    "assists": 0,
    "headshots": 0,
    "series_wins": 0,
    "series_losses": 0,
    "playlists": {}
  },
  "795707878388137995": {
    "discord_name": "Sauce",
    "alias": "",
    "twitch_name": "",
    "twitch_url": "",
    "rank": 1,
    "highest_rank": 1,
    "xp": 0,
    "mmr": 900,
    "wins": 0,
    "losses": 0,
    "total_games": 0,
    "kills": 0,
    "deaths": 0,
    "assists": 0,
    "headshots": 0,
    "series_wins": 0,
    "series_losses": 0,
    "playlists": {}
  },
  "241980128631062539": {
    "discord_name": "Conflictz",
    "alias": "",
    "twitch_name": "",
    "twitch_url": "",
    "rank": 1,
    "highest_rank": 1,
    "xp": 0,
    "mmr": 700,
    "wins": 0,
    "losses": 0,
    "total_games": 0,
    "kills": 0,
    "deaths": 0,
    "assists": 0,
    "headshots": 0,
    "series_wins": 0,
    "series_losses": 0,
    "playlists": {}
  },
  "694412691015598140": {
    "discord_name": "simon hagiwara",
    "alias": "",
    "twitch_name": "spencerbrown",
    "twitch_url": "https://twitch.tv/spencerbrown",
    "rank": 1,
    "highest_rank": 1,
    "xp": 0,
    "mmr": 700,
    "wins": 0,
    "losses": 0,
    "total_games": 0,
    "kills": 0,
    "deaths": 0,
    "assists": 0,
    "headshots": 0,
    "series_wins": 0,
    "series_losses": 0,
    "playlists": {}
  },
  "851303681897791548": {
    "discord_name": "Genkinz",
    "alias": "",
    "twitch_name": "genkinz",
    "twitch_url": "https://twitch.tv/genkinz",
    "rank": 1,
    "highest_rank": 1,
    "xp": 0,
    "mmr": 249,
    "wins": 0,
    "losses": 0,
    "total_games": 0,
    "kills": 0,
    "deaths": 0,
    "assists": 0,
    "headshots": 0,
    "series_wins": 0,
    "series_losses": 0,
    "playlists": {}
  },
  "1351057247437852733": {
    "discord_name": "GoonerRat",
    "alias": "",
    "twitch_name": "",
    "twitch_url": "",
    "rank": 1,
    "highest_rank": 1,
    "xp": 0,
    "mmr": 1000,
    "wins": 0,
    "losses": 0,
    "total_games": 0,
    "kills": 0,
    "deaths": 0,
    "assists": 0,
    "headshots": 0,
    "series_wins": 0,
    "series_losses": 0,
    "playlists": {}
  },
  "736026857572401214": {
    "discord_name": "heyitsarcadia",
    "alias": "",
    "twitch_name": "",
    "twitch_url": "",
    "rank": 1,
    "highest_rank": 1,
    "xp": 0,
    "mmr": 400,
    "wins": 0,
    "losses": 0,
    "total_games": 0,
    "kills": 0,
    "deaths": 0,
    "assists": 0,
    "headshots": 0,
    "series_wins": 0,
    "series_losses": 0,
    "playlists": {}
  },
  "359472455259127820": {
    "discord_name": "GT: HeroicFool69 (Stormcrow2)",
    "alias": "",
    "twitch_name": "",
    "twitch_url": "",
    "rank": 1,
    "highest_rank": 1,
    "xp": 0,
    "mmr": 500,
    "wins": 0,
    "losses": 0,
    "total_games": 0,
    "kills": 0,
    "deaths": 0,
    "assists": 0,
    "headshots": 0,
    "series_wins": 0,
    "series_losses": 0,
    "playlists": {}
  },
  "1126543913654698044": {
    "discord_name": "Skaduf The Greatest Halo Player",
    "alias": "",
    "twitch_name": "skaduf",
    "twitch_url": "https://twitch.tv/skaduf",
    "rank": 1,
    "highest_rank": 1,
    "xp": 0,
    "mmr": 500,
    "wins": 0,
    "losses": 0,
    "total_games": 0,
    "kills": 0,
    "deaths": 0,
    "assists": 0,
    "headshots": 0,
    "series_wins": 0,
    "series_losses": 0,
    "playlists": {}
  },
  "1118666385921425478": {
    "discord_name": "oKrazed",
    "alias": "",
    "twitch_name": "",
    "twitch_url": "",
    "rank": 1,
    "highest_rank": 1,
    "xp": 0,
    "mmr": 500,
    "wins": 0,
    "losses": 0,
    "total_games": 0,
    "kills": 0,
    "deaths": 0,
    "assists": 0,
    "headshots": 0,
    "series_wins": 0,
    "series_losses": 0,
    "playlists": {}
  },
  "1155320421672046672": {
    "discord_name": "Csquared",
    "alias": "",
    "twitch_name": "",
    "twitch_url": "",
    "rank": 1,
    "highest_rank": 1,
    "xp": 0,
    "mmr": 750,
    "wins": 0,
    "losses": 0,
    "total_games": 0,
    "kills": 0,
    "deaths": 0,
    "assists": 0,
    "headshots": 0,
    "series_wins": 0,
    "series_losses": 0,
    "playlists": {}
  },
  "1258601786533609554": {
    "discord_name": "Burn iTz",
    "alias": "",
    "twitch_name": "",
    "twitch_url": "",
    "rank": 1,
    "highest_rank": 1,
    "xp": 0,
    "mmr": 900,
    "wins": 0,
    "losses": 0,
    "total_games": 0,
    "kills": 0,
    "deaths": 0,
    "assists": 0,
    "headshots": 0,
    "series_wins": 0,
    "series_losses": 0,
    "playlists": {}
  },
  "710585633474740306": {
    "discord_name": "VirulentGrunt",
    "alias": "",
    "twitch_name": "",
    "twitch_url": "",
    "rank": 1,
    "highest_rank": 1,
    "xp": 0,
    "mmr": 1000,
    "wins": 0,
    "losses": 0,
    "total_games": 0,
    "kills": 0,
    "deaths": 0,
    "assists": 0,
    "headshots": 0,
    "series_wins": 0,
    "series_losses": 0,
    "playlists": {}
  },
  "1051302763633573978": {
    "discord_name": "NomeOGx3",
    "alias": "",
    "twitch_name": "",
    "twitch_url": "",
    "rank": 1,
    "highest_rank": 1,
    "xp": 0,
    "mmr": 750,
    "wins": 0,
    "losses": 0,
    "total_games": 0,
    "kills": 0,
    "deaths": 0,
    "assists": 0,
    "headshots": 0,
    "series_wins": 0,
    "series_losses": 0,
    "playlists": {}
  },
  "1218796844088430692": {
    "discord_name": "ll Legend ll",
    "alias": "",
    "twitch_name": "LtzLegend_",
    "twitch_url": "https://twitch.tv/LtzLegend_",
    "rank": 1,
    "highest_rank": 1,
    "xp": 0,
    "mmr": 725,
    "wins": 0,
    "losses": 0,
    "total_games": 0,
    "kills": 0,
    "deaths": 0,
    "assists": 0,
    "headshots": 0,
    "series_wins": 0,
    "series_losses": 0,
    "playlists": {}
  },
  "1343263695769305190": {
    "discord_name": "Lux",
    "alias": "",
    "twitch_name": "",
    "twitch_url": "",
    "rank": 1,
    "highest_rank": 1,
    "xp": 0,
    "mmr": 100,
    "wins": 0,
    "losses": 0,
    "total_games": 0,
    "kills": 0,
    "deaths": 0,
    "assists": 0,
    "headshots": 0,
    "series_wins": 0,
    "series_losses": 0,
    "playlists": {}
  },
  "1233040240210477160": {
    "discord_name": "TeoulisComple \ud83c\uddec\ud83c\uddf7",
    "alias": "happyhippoheythere",
    "twitch_name": "teouliscompleq",
    "twitch_url": "https://twitch.tv/teouliscompleq",
    "rank": 1,
    "highest_rank": 1,
    "xp": 0,
    "mmr": 600,
    "wins": 0,
    "losses": 0,
    "total_games": 0,
    "kills": 0,
    "deaths": 0,
    "assists": 0,
    "headshots": 0,
    "series_wins": 0,
    "series_losses": 0,
    "playlists": {}
  },
  "196752652569149440": {
    "discord_name": "BliNdFiRe",
    "alias": "",
    "twitch_name": "",
    "twitch_url": "",
    "rank": 1,
    "highest_rank": 1,
    "xp": 0,
    "mmr": 1200,
    "wins": 0,
    "losses": 0,
    "total_games": 0,
    "kills": 0,
    "deaths": 0,
    "assists": 0,
    "headshots": 0,
    "series_wins": 0,
    "series_losses": 0,
    "playlists": {}
  },
  "1348067996761063535": {
    "discord_name": "Zony",
    "alias": "",
    "twitch_name": "",
    "twitch_url": "",
    "rank": 1,
    "highest_rank": 1,
    "xp": 0,
    "mmr": 850,
    "wins": 0,
    "losses": 0,
    "total_games": 0,
    "kills": 0,
    "deaths": 0,
    "assists": 0,
    "headshots": 0,
    "series_wins": 0,
    "series_losses": 0,
    "playlists": {}
  },
  "1393893716338540675": {
    "discord_name": "lzl WeakSide",
    "alias": "",
    "twitch_name": "",
    "twitch_url": "",
    "rank": 1,
    "highest_rank": 1,
    "xp": 0,
    "mmr": 600,
    "wins": 0,
    "losses": 0,
    "total_games": 0,
    "kills": 0,
    "deaths": 0,
    "assists": 0,
    "headshots": 0,
    "series_wins": 0,
    "series_losses": 0,
    "playlists": {}
  },
  "161726300304834560": {
    "discord_name": "shooter22",
    "alias": "shooter22",
    "twitch_name": "",
    "twitch_url": "",
    "rank": 4,
    "highest_rank": 4,
    "xp": 371,
    "mmr": 500,
    "wins": 4,
    "losses": 5,
    "total_games": 13,
    "kills": 154,
    "deaths": 224,
    "assists": 122,
    "headshots": 115,
    "series_wins": 1,
    "series_losses": 1,
    "playlists": {
      "MLG 4v4": {
        "rank": 4,
        "highest_rank": 4,
        "xp": 371,
        "wins": 4,
        "losses": 5,
        "games": 11
      }
    }
  },
  "210280313262309376": {
    "discord_name": "Grave",
    "alias": "",
    "twitch_name": "",
    "twitch_url": "",
    "rank": 1,
    "highest_rank": 1,
    "xp": 0,
    "mmr": 1050,
    "wins": 0,
    "losses": 0,
    "total_games": 0,
    "kills": 0,
    "deaths": 0,
    "assists": 0,
    "headshots": 0,
    "series_wins": 0,
    "series_losses": 0,
    "playlists": {}
  },
  "174522691917840384": {
    "discord_name": "BxSouljah",
    "alias": "",
    "twitch_name": "",
    "twitch_url": "",
    "rank": 1,
    "highest_rank": 1,
    "xp": 0,
    "mmr": 900,
    "wins": 0,
    "losses": 0,
    "total_games": 0,
    "kills": 0,
    "deaths": 0,
    "assists": 0,
    "headshots": 0,
    "series_wins": 0,
    "series_losses": 0,
    "playlists": {}
  },
  "154836949964816384": {
    "discord_name": "H4",
    "alias": "",
    "twitch_name": "",
    "twitch_url": "",
    "rank": 1,
    "highest_rank": 1,
    "xp": 0,
    "mmr": 900,
    "wins": 0,
    "losses": 0,
    "total_games": 0,
    "kills": 0,
    "deaths": 0,
    "assists": 0,
    "headshots": 0,
    "series_wins": 0,
    "series_losses": 0,
    "playlists": {}
  },
  "198564445105029120": {
    "discord_name": "Vonlionton",
    "alias": "",
    "twitch_name": "",
    "twitch_url": "",
    "rank": 1,
    "highest_rank": 1,
    "xp": 0,
    "mmr": 750,
    "wins": 0,
    "losses": 0,
    "total_games": 0,
    "kills": 0,
    "deaths": 0,
    "assists": 0,
    "headshots": 0,
    "series_wins": 0,
    "series_losses": 0,
    "playlists": {}
  },
  "205738438773833728": {
    "discord_name": "Xanticity",
    "alias": "",
    "twitch_name": "",
    "twitch_url": "",
    "rank": 1,
    "highest_rank": 1,
    "xp": 0,
    "mmr": 1400,
    "wins": 0,
    "losses": 0,
    "total_games": 0,
    "kills": 0,
    "deaths": 0,
    "assists": 0,
    "headshots": 0,
    "series_wins": 0,
    "series_losses": 0,
    "playlists": {}
  },
  "799264724021280768": {
    "discord_name": "SoldieR",
    "alias": "",
    "twitch_name": "",
    "twitch_url": "",
    "rank": 1,
    "highest_rank": 1,
    "xp": 0,
    "mmr": 750,
    "wins": 0,
    "losses": 0,
    "total_games": 0,
    "kills": 0,
    "deaths": 0,
    "assists": 0,
    "headshots": 0,
    "series_wins": 0,
    "series_losses": 0,
    "playlists": {}
  },
  "164725201907613696": {
    "discord_name": "James | The Frenetic",
    "alias": "",
    "twitch_name": "thefrenetic",
    "twitch_url": "https://twitch.tv/thefrenetic",
    "rank": 2,
    "highest_rank": 3,
    "xp": 183,
    "mmr": 1350,
    "wins": 2,
    "losses": 8,
    "total_games": 12,
    "kills": 321,
    "deaths": 309,
    "assists": 170,
    "headshots": 235,
    "series_wins": 0,
    "series_losses": 2,
    "playlists": {
      "MLG 4v4": {
        "rank": 2,
        "highest_rank": 3,
        "xp": 183,
        "wins": 2,
        "losses": 8,
        "games": 10
      }
    }
  },
  "135116534388490240": {
    "discord_name": "J1",
    "alias": "",
    "twitch_name": "",
    "twitch_url": "",
    "rank": 1,
    "highest_rank": 1,
    "xp": 0,
    "mmr": 850,
    "wins": 0,
    "losses": 0,
    "total_games": 0,
    "kills": 0,
    "deaths": 0,
    "assists": 0,
    "headshots": 0,
    "series_wins": 0,
    "series_losses": 0,
    "playlists": {}
  },
  "296360818465964032": {
    "discord_name": "Pinesauce",
    "alias": "",
    "twitch_name": "",
    "twitch_url": "",
    "rank": 1,
    "highest_rank": 1,
    "xp": 0,
    "mmr": 650,
    "wins": 0,
    "losses": 0,
    "total_games": 0,
    "kills": 0,
    "deaths": 0,
    "assists": 0,
    "headshots": 0,
    "series_wins": 0,
    "series_losses": 0,
    "playlists": {}
  },
  "1040724126836457624": {
    "discord_name": "Em Won 5 F 1 T",
    "alias": "Em Won 5 F 1 T",
    "twitch_name": "",
    "twitch_url": "",
    "rank": 8,
    "highest_rank": 5,
    "xp": 693,
    "mmr": 463,
    "wins": 7,
    "losses": 1,
    "total_games": 11,
    "kills": 182,
    "deaths": 211,
    "assists": 112,
    "headshots": 139,
    "series_wins": 2,
    "series_losses": 0,
    "playlists": {
      "MLG 4v4": {
        "rank": 8,
        "highest_rank": 5,
        "xp": 693,
        "wins": 7,
        "losses": 1,
        "games": 9
      }
    }
  },
  "653385687852253215": {
    "discord_name": "DomerSimpson",
    "alias": "domer_simpson",
    "twitch_name": "domer_simpson_",
    "twitch_url": "https://twitch.tv/domer_simpson_",
    "rank": 1,
    "highest_rank": 1,
    "xp": 0,
    "mmr": 600,
    "wins": 0,
    "losses": 0,
    "total_games": 0,
    "kills": 0,
    "deaths": 0,
    "assists": 0,
    "headshots": 0,
    "series_wins": 0,
    "series_losses": 0,
    "playlists": {}
  },
  "352157745530667009": {
    "discord_name": "TwoCaribous",
    "alias": "",
    "twitch_name": "",
    "twitch_url": "",
    "rank": 1,
    "highest_rank": 1,
    "xp": 0,
    "mmr": 600,
    "wins": 0,
    "losses": 0,
    "total_games": 0,
    "kills": 0,
    "deaths": 0,
    "assists": 0,
    "headshots": 0,
    "series_wins": 0,
    "series_losses": 0,
    "playlists": {}
  },
  "274372368686776321": {
    "discord_name": "sneakybeav3r",
    "alias": "",
    "twitch_name": "SneeakyBeav3r",
    "twitch_url": "https://twitch.tv/SneeakyBeav3r",
    "rank": 7,
    "highest_rank": 8,
    "xp": 673,
    "mmr": 1400,
    "wins": 8,
    "losses": 8,
    "total_games": 20,
    "kills": 407,
    "deaths": 318,
    "assists": 188,
    "headshots": 269,
    "series_wins": 2,
    "series_losses": 1,
    "playlists": {
      "MLG 4v4": {
        "rank": 7,
        "highest_rank": 8,
        "xp": 673,
        "wins": 8,
        "losses": 8,
        "games": 18
      }
    }
  },
  "156973309722886144": {
    "discord_name": "LD50 II",
    "alias": "ld50_ii",
    "twitch_name": "LD50_II",
    "twitch_url": "https://twitch.tv/LD50_II",
    "rank": 1,
    "highest_rank": 1,
    "xp": 0,
    "mmr": 450,
    "wins": 0,
    "losses": 0,
    "total_games": 0,
    "kills": 0,
    "deaths": 0,
    "assists": 0,
    "headshots": 0,
    "series_wins": 0,
    "series_losses": 0,
    "playlists": {}
  },
  "173928028173369345": {
    "discord_name": "ZeeD",
    "alias": "",
    "twitch_name": "",
    "twitch_url": "",
    "rank": 1,
    "highest_rank": 1,
    "xp": 0,
    "mmr": 1100,
    "wins": 0,
    "losses": 0,
    "total_games": 0,
    "kills": 0,
    "deaths": 0,
    "assists": 0,
    "headshots": 0,
    "series_wins": 0,
    "series_losses": 0,
    "playlists": {}
  },
  "175415359703089152": {
    "discord_name": "Obi Juan",
    "alias": "",
    "twitch_name": "defensevpower",
    "twitch_url": "https://twitch.tv/defensevpower",
    "rank": 1,
    "highest_rank": 1,
    "xp": 0,
    "mmr": 1350,
    "wins": 0,
    "losses": 0,
    "total_games": 0,
    "kills": 0,
    "deaths": 0,
    "assists": 0,
    "headshots": 0,
    "series_wins": 0,
    "series_losses": 0,
    "playlists": {}
  },
  "390747330631958528": {
    "discord_name": "cOn",
    "alias": "cOn",
    "twitch_name": "",
    "twitch_url": "",
    "rank": 9,
    "highest_rank": 9,
    "xp": 861,
    "mmr": 1750,
    "wins": 10,
    "losses": 7,
    "total_games": 19,
    "kills": 413,
    "deaths": 372,
    "assists": 288,
    "headshots": 271,
    "series_wins": 2,
    "series_losses": 1,
    "playlists": {
      "MLG 4v4": {
        "rank": 9,
        "highest_rank": 9,
        "xp": 861,
        "wins": 10,
        "losses": 7,
        "games": 17
      }
    }
  },
  "180809401228197889": {
    "discord_name": "StoRmY v2",
    "alias": "",
    "twitch_name": "Stormy_v2",
    "twitch_url": "https://twitch.tv/Stormy_v2",
    "rank": 1,
    "highest_rank": 1,
    "xp": 0,
    "mmr": 2000,
    "wins": 0,
    "losses": 0,
    "total_games": 0,
    "kills": 0,
    "deaths": 0,
    "assists": 0,
    "headshots": 0,
    "series_wins": 0,
    "series_losses": 0,
    "playlists": {}
  },
  "164177623163994113": {
    "discord_name": "WildCherry",
    "alias": "",
    "twitch_name": "",
    "twitch_url": "",
    "rank": 1,
    "highest_rank": 1,
    "xp": 0,
    "mmr": 1150,
    "wins": 0,
    "losses": 0,
    "total_games": 0,
    "kills": 0,
    "deaths": 0,
    "assists": 0,
    "headshots": 0,
    "series_wins": 0,
    "series_losses": 0,
    "playlists": {}
  },
  "174366760479358976": {
    "discord_name": "Mathlete",
    "alias": "",
    "twitch_name": "",
    "twitch_url": "",
    "rank": 1,
    "highest_rank": 1,
    "xp": 0,
    "mmr": 1100,
    "wins": 0,
    "losses": 0,
    "total_games": 0,
    "kills": 0,
    "deaths": 0,
    "assists": 0,
    "headshots": 0,
    "series_wins": 0,
    "series_losses": 0,
    "playlists": {}
  },
  "107703779188580352": {
    "discord_name": "helldotcom",
    "alias": "",
    "twitch_name": "",
    "twitch_url": "",
    "rank": 1,
    "highest_rank": 1,
    "xp": 0,
    "mmr": 1176,
    "wins": 0,
    "losses": 0,
    "total_games": 0,
    "kills": 0,
    "deaths": 0,
    "assists": 0,
    "headshots": 0,
    "series_wins": 0,
    "series_losses": 0,
    "playlists": {}
  },
  "111190770756657152": {
    "discord_name": "EpiiiC",
    "alias": "EpiiiC",
    "twitch_name": "e212",
    "twitch_url": "https://twitch.tv/e212",
    "rank": 9,
    "highest_rank": 10,
    "xp": 847,
    "mmr": 1400,
    "wins": 10,
    "losses": 12,
    "total_games": 24,
    "kills": 555,
    "deaths": 501,
    "assists": 343,
    "headshots": 394,
    "series_wins": 2,
    "series_losses": 2,
    "playlists": {
      "MLG 4v4": {
        "rank": 9,
        "highest_rank": 10,
        "xp": 847,
        "wins": 10,
        "losses": 12,
        "games": 22
      }
    }
  },
  "84785392234012672": {
    "discord_name": "re4thewin",
    "alias": "",
    "twitch_name": "",
    "twitch_url": "",
    "rank": 1,
    "highest_rank": 1,
    "xp": 0,
    "mmr": 800,
    "wins": 0,
    "losses": 0,
    "total_games": 0,
    "kills": 0,
    "deaths": 0,
    "assists": 0,
    "headshots": 0,
    "series_wins": 0,
    "series_losses": 0,
    "playlists": {}
  },
  "335626718062837760": {
    "discord_name": "LosOjosRojos",
    "alias": "losojosrojos",
    "twitch_name": "LosOjosRojos_H2",
    "twitch_url": "https://twitch.tv/LosOjosRojos_H2",
    "rank": 1,
    "highest_rank": 1,
    "xp": 0,
    "mmr": 600,
    "wins": 0,
    "losses": 0,
    "total_games": 0,
    "kills": 0,
    "deaths": 0,
    "assists": 0,
    "headshots": 0,
    "series_wins": 0,
    "series_losses": 0,
    "playlists": {}
  },
  "291104674839527424": {
    "discord_name": "Siko",
    "alias": "",
    "twitch_name": "",
    "twitch_url": "",
    "rank": 1,
    "highest_rank": 1,
    "xp": 0,
    "mmr": 1000,
    "wins": 0,
    "losses": 0,
    "total_games": 0,
    "kills": 0,
    "deaths": 0,
    "assists": 0,
    "headshots": 0,
    "series_wins": 0,
    "series_losses": 0,
    "playlists": {}
  },
  "301971773077848064": {
    "discord_name": "Korin",
    "alias": "",
    "twitch_name": "",
    "twitch_url": "",
    "rank": 1,
    "highest_rank": 1,
    "xp": 0,
    "mmr": 100,
    "wins": 0,
    "losses": 0,
    "total_games": 0,
    "kills": 0,
    "deaths": 0,
    "assists": 0,
    "headshots": 0,
    "series_wins": 0,
    "series_losses": 0,
    "playlists": {}
  },
  "188009416556150784": {
    "discord_name": "side",
    "alias": "",
    "twitch_name": "",
    "twitch_url": "",
    "rank": 1,
    "highest_rank": 1,
    "xp": 0,
    "mmr": 1450,
    "wins": 0,
    "losses": 0,
    "total_games": 0,
    "kills": 0,
    "deaths": 0,
    "assists": 0,
    "headshots": 0,
    "series_wins": 0,
    "series_losses": 0,
    "playlists": {}
  },
  "772288046905032704": {
    "discord_name": "UltiMeGa",
    "alias": "",
    "twitch_name": "",
    "twitch_url": "",
    "rank": 1,
    "highest_rank": 1,
    "xp": 0,
    "mmr": 1300,
    "wins": 0,
    "losses": 0,
    "total_games": 0,
    "kills": 0,
    "deaths": 0,
    "assists": 0,
    "headshots": 0,
    "series_wins": 0,
    "series_losses": 0,
    "playlists": {}
  },
  "598584495641198592": {
    "discord_name": "Welchs",
    "alias": "",
    "twitch_name": "",
    "twitch_url": "",
    "rank": 1,
    "highest_rank": 1,
    "xp": 0,
    "mmr": 1500,
    "wins": 0,
    "losses": 0,
    "total_games": 0,
    "kills": 0,
    "deaths": 0,
    "assists": 0,
    "headshots": 0,
    "series_wins": 0,
    "series_losses": 0,
    "playlists": {}
  },
  "167766278860177408": {
    "discord_name": "CYRiX",
    "alias": "",
    "twitch_name": "",
    "twitch_url": "",
    "rank": 1,
    "highest_rank": 1,
    "xp": 0,
    "mmr": 800,
    "wins": 0,
    "losses": 0,
    "total_games": 0,
    "kills": 0,
    "deaths": 0,
    "assists": 0,
    "headshots": 0,
    "series_wins": 0,
    "series_losses": 0,
    "playlists": {}
  },
  "177913649728323584": {
    "discord_name": "Kryptonite",
    "alias": "",
    "twitch_name": "slikryptoniite",
    "twitch_url": "https://twitch.tv/slikryptoniite",
    "rank": 1,
    "highest_rank": 1,
    "xp": 0,
    "mmr": 1500,
    "wins": 0,
    "losses": 0,
    "total_games": 0,
    "kills": 0,
    "deaths": 0,
    "assists": 0,
    "headshots": 0,
    "series_wins": 0,
    "series_losses": 0,
    "playlists": {}
  },
  "187356723135119360": {
    "discord_name": "Cortalisk",
    "alias": "",
    "twitch_name": "",
    "twitch_url": "",
    "rank": 1,
    "highest_rank": 1,
    "xp": 0,
    "mmr": 1000,
    "wins": 0,
    "losses": 0,
    "total_games": 0,
    "kills": 0,
    "deaths": 0,
    "assists": 0,
    "headshots": 0,
    "series_wins": 0,
    "series_losses": 0,
    "playlists": {}
  },
  "155302533345050624": {
    "discord_name": "Famous",
    "alias": "",
    "twitch_name": "",
    "twitch_url": "",
    "rank": 1,
    "highest_rank": 1,
    "xp": 0,
    "mmr": 1500,
    "wins": 0,
    "losses": 0,
    "total_games": 0,
    "kills": 0,
    "deaths": 0,
    "assists": 0,
    "headshots": 0,
    "series_wins": 0,
    "series_losses": 0,
    "playlists": {}
  },
  "168151188741685248": {
    "discord_name": "AfroMaN",
    "alias": "AfroMaN",
    "twitch_name": "",
    "twitch_url": "",
    "rank": 7,
    "highest_rank": 7,
    "xp": 663,
    "mmr": 1200,
    "wins": 7,
    "losses": 10,
    "total_games": 20,
    "kills": 466,
    "deaths": 368,
    "assists": 261,
    "headshots": 311,
    "series_wins": 2,
    "series_losses": 2,
    "playlists": {
      "MLG 4v4": {
        "rank": 7,
        "highest_rank": 7,
        "xp": 663,
        "wins": 7,
        "losses": 10,
        "games": 18
      }
    }
  },
  "269681242335739905": {
    "discord_name": "keylord",
    "alias": "keylord",
    "twitch_name": "justinkeylord",
    "twitch_url": "https://twitch.tv/justinkeylord",
    "rank": 8,
    "highest_rank": 6,
    "xp": 704,
    "mmr": 750,
    "wins": 8,
    "losses": 22,
    "total_games": 35,
    "kills": 517,
    "deaths": 709,
    "assists": 435,
    "headshots": 340,
    "series_wins": 0,
    "series_losses": 6,
    "playlists": {
      "MLG 4v4": {
        "rank": 8,
        "highest_rank": 6,
        "xp": 704,
        "wins": 8,
        "losses": 22,
        "games": 31
      }
    }
  },
  "175060415833833472": {
    "discord_name": "Josiah",
    "alias": "Tetracide",
    "twitch_name": "",
    "twitch_url": "",
    "rank": 4,
    "highest_rank": 4,
    "xp": 296,
    "mmr": 750,
    "wins": 3,
    "losses": 2,
    "total_games": 5,
    "kills": 97,
    "deaths": 79,
    "assists": 48,
    "headshots": 69,
    "series_wins": 1,
    "series_losses": 0,
    "playlists": {
      "MLG 4v4": {
        "rank": 4,
        "highest_rank": 4,
        "xp": 296,
        "wins": 3,
        "losses": 2,
        "games": 5
      }
    }
  }
}